palpy.cpython-39-x86_64-linux-gnu.so
palpy-1.8.4.dist-info/COPYING
palpy-1.8.4.dist-info/RECORD
palpy-1.8.4.dist-info/WHEEL
palpy-1.8.4.dist-info/top_level.txt
palpy-1.8.4.dist-info/METADATA
