Metadata-Version: 2.1
Name: palpy
Version: 1.8.4
Summary: PAL -- A Positional Astronomy Library
Author-email: Tim Jenness <tim.jenness@gmail.com>
License: GPLv2 License
Project-URL: Homepage, https://github.com/Starlink/palpy
Keywords: Starlink
Classifier: Intended Audience :: Science/Research
Classifier: License :: OSI Approved :: GNU General Public License v2 (GPLv2)
Classifier: Programming Language :: Cython
Classifier: Programming Language :: Python
Classifier: Programming Language :: Python :: 3
Classifier: Programming Language :: C
Classifier: Programming Language :: Python :: Implementation :: CPython
Classifier: Topic :: Scientific/Engineering :: Astronomy
License-File: COPYING
Requires-Dist: numpy
